Workbook

Sheet Summary
A1: DSA Practice Tracker - 16-Week Plan (Java)
A2: Update only the Status, Date Solved and Notes columns in the other two sheets. Everything on this sheet recalculates automatically.
A4: Topic | B4: Total | C4: Solved | D4: Remaining | E4: % Done
A5: 1. Conditional Statements | B5: =COUNTIF('LeetCode Tracker'!$D$2:$D$209,A5) -> 8 | C5: =COUNTIFS('LeetCode Tracker'!$D$2:$D$209,A5,'LeetCode Tracker'!$H$2:$H$209,"Solved") -> 1 | D5: =B5-C5 -> 7 | E5: =IF(B5=0,0,C5/B5) -> 0.125
A6: 2. Loops and Basic Math | B6: =COUNTIF('LeetCode Tracker'!$D$2:$D$209,A6) -> 17 | C6: =COUNTIFS('LeetCode Tracker'!$D$2:$D$209,A6,'LeetCode Tracker'!$H$2:$H$209,"Solved") -> 0 | D6: =B6-C6 -> 17 | E6: =IF(B6=0,0,C6/B6) -> 0
A7: 3. Arrays | B7: =COUNTIF('LeetCode Tracker'!$D$2:$D$209,A7) -> 20 | C7: =COUNTIFS('LeetCode Tracker'!$D$2:$D$209,A7,'LeetCode Tracker'!$H$2:$H$209,"Solved") -> 0 | D7: =B7-C7 -> 20 | E7: =IF(B7=0,0,C7/B7) -> 0
A8: 4. Strings | B8: =COUNTIF('LeetCode Tracker'!$D$2:$D$209,A8) -> 11 | C8: =COUNTIFS('LeetCode Tracker'!$D$2:$D$209,A8,'LeetCode Tracker'!$H$2:$H$209,"Solved") -> 0 | D8: =B8-C8 -> 11 | E8: =IF(B8=0,0,C8/B8) -> 0
A9: 5. Hashing | B9: =COUNTIF('LeetCode Tracker'!$D$2:$D$209,A9) -> 7 | C9: =COUNTIFS('LeetCode Tracker'!$D$2:$D$209,A9,'LeetCode Tracker'!$H$2:$H$209,"Solved") -> 0 | D9: =B9-C9 -> 7 | E9: =IF(B9=0,0,C9/B9) -> 0
A10: 6. Two Pointers and Sliding Window | B10: =COUNTIF('LeetCode Tracker'!$D$2:$D$209,A10) -> 11 | C10: =COUNTIFS('LeetCode Tracker'!$D$2:$D$209,A10,'LeetCode Tracker'!$H$2:$H$209,"Solved") -> 0 | D10: =B10-C10 -> 11 | E10: =IF(B10=0,0,C10/B10) -> 0
A11: 7. Prefix Sum | B11: =COUNTIF('LeetCode Tracker'!$D$2:$D$209,A11) -> 5 | C11: =COUNTIFS('LeetCode Tracker'!$D$2:$D$209,A11,'LeetCode Tracker'!$H$2:$H$209,"Solved") -> 0 | D11: =B11-C11 -> 5 | E11: =IF(B11=0,0,C11/B11) -> 0
A12: 8. Binary Search | B12: =COUNTIF('LeetCode Tracker'!$D$2:$D$209,A12) -> 11 | C12: =COUNTIFS('LeetCode Tracker'!$D$2:$D$209,A12,'LeetCode Tracker'!$H$2:$H$209,"Solved") -> 0 | D12: =B12-C12 -> 11 | E12: =IF(B12=0,0,C12/B12) -> 0
A13: 9. Sorting | B13: =COUNTIF('LeetCode Tracker'!$D$2:$D$209,A13) -> 4 | C13: =COUNTIFS('LeetCode Tracker'!$D$2:$D$209,A13,'LeetCode Tracker'!$H$2:$H$209,"Solved") -> 0 | D13: =B13-C13 -> 4 | E13: =IF(B13=0,0,C13/B13) -> 0
A14: 10. Recursion and Backtracking | B14: =COUNTIF('LeetCode Tracker'!$D$2:$D$209,A14) -> 11 | C14: =COUNTIFS('LeetCode Tracker'!$D$2:$D$209,A14,'LeetCode Tracker'!$H$2:$H$209,"Solved") -> 0 | D14: =B14-C14 -> 11 | E14: =IF(B14=0,0,C14/B14) -> 0
A15: 11. Linked List | B15: =COUNTIF('LeetCode Tracker'!$D$2:$D$209,A15) -> 14 | C15: =COUNTIFS('LeetCode Tracker'!$D$2:$D$209,A15,'LeetCode Tracker'!$H$2:$H$209,"Solved") -> 0 | D15: =B15-C15 -> 14 | E15: =IF(B15=0,0,C15/B15) -> 0
A16: 12. Stack and Queue | B16: =COUNTIF('LeetCode Tracker'!$D$2:$D$209,A16) -> 11 | C16: =COUNTIFS('LeetCode Tracker'!$D$2:$D$209,A16,'LeetCode Tracker'!$H$2:$H$209,"Solved") -> 0 | D16: =B16-C16 -> 11 | E16: =IF(B16=0,0,C16/B16) -> 0
... A25: 21. Very Advanced | B25: =COUNTIF('LeetCode Tracker'!$D$2:$D$209,A25) -> 4 | C25: =COUNTIFS('LeetCode Tracker'!$D$2:$D$209,A25,'LeetCode Tracker'!$H$2:$H$209,"Solved") -> 0 | D25: =B25-C25 -> 4 | E25: =IF(B25=0,0,C25/B25) -> 0
A26: TOTAL (LeetCode) | B26: =SUM(B5:B25) -> 208 | C26: =SUM(C5:C25) -> 1 | D26: =B26-C26 -> 207 | E26: =IF(B26=0,0,C26/B26) -> 0.0048076923
A28: Difficulty | B28: Total | C28: Solved | D28: Remaining | E28: % Done
A29: Easy | B29: =COUNTIF('LeetCode Tracker'!$G$2:$G$209,A29) -> 79 | C29: =COUNTIFS('LeetCode Tracker'!$G$2:$G$209,A29,'LeetCode Tracker'!$H$2:$H$209,"Solved") -> 1 | D29: =B29-C29 -> 78 | E29: =IF(B29=0,0,C29/B29) -> 0.012658228
A30: Medium | B30: =COUNTIF('LeetCode Tracker'!$G$2:$G$209,A30) -> 104 | C30: =COUNTIFS('LeetCode Tracker'!$G$2:$G$209,A30,'LeetCode Tracker'!$H$2:$H$209,"Solved") -> 0 | D30: =B30-C30 -> 104 | E30: =IF(B30=0,0,C30/B30) -> 0
A31: Hard | B31: =COUNTIF('LeetCode Tracker'!$G$2:$G$209,A31) -> 25 | C31: =COUNTIFS('LeetCode Tracker'!$G$2:$G$209,A31,'LeetCode Tracker'!$H$2:$H$209,"Solved") -> 0 | D31: =B31-C31 -> 25 | E31: =IF(B31=0,0,C31/B31) -> 0
A33: Other Counters | B33: Total | C33: Solved | D33: Remaining | E33: % Done
A34: Extra Practice (GFG / HR / CC / CSES / AtCoder) | B34: =COUNTA('Extra Practice'!$E$2:$E$130) -> 129 | C34: =COUNTIF('Extra Practice'!$F$2:$F$130,"Solved") -> 0 | D34: =B34-C34 -> 129 | E34: =IF(B34=0,0,C34/B34) -> 0
A35: LeetCode problems marked 'Needs Revision' | B35: =COUNTIF('LeetCode Tracker'!$H$2:$H$209,"Needs Revision") -> 0
A36: Phase 0: Logic Building (before DSA) | B36: =COUNTA('Logic Building'!$D$2:$D$90) -> 89 | C36: =COUNTIF('Logic Building'!$F$2:$F$90,"Solved") -> 0 | D36: =B36-C36 -> 89 | E36: =IF(B36=0,0,C36/B36) -> 0
A38: How to use
A39: 1. Open 'LeetCode Tracker' and pick Status from the dropdown (Not Started / In Progress / Solved / Needs Revision).
A40: 2. Type Date Solved as 27-Oct-2026 (day-month-year). Use Notes for the approach and time/space complexity.
A41: 3. Click the LC No to open a LeetCode search for that problem number.
A42: 4. Follow the Week column in order. Use the filter arrows on the header row to see one week or topic at a time.
A43: 5. 'Extra Practice' lists the same-topic problems from GFG, HackerRank, CodeChef, SPOJ, CSES and AtCoder.
A44: Note: LC 136 (Single Number) belongs to both Arrays and Bit Manipulation, so it is listed once, under Arrays (Week 2).
A45: Note: Combined entries such as 94/144/145, 235/236 and 207/210 are split into separate rows so each can be tracked.
A46: Start with the 'Logic Building' sheet (10 days) before Week 1 of the DSA plan. See 'Logic Plan & Interview' for the interview approach.

Sheet Logic Building
A1: S.No | B1: Day | C1: Topic | D1: Problem | E1: Practice On | F1: Status | G1: Date Solved | H1: Notes
A2: 1 | B2: 1 | C2: Java basics, I/O and conditions | D2: Swap two numbers (with and without a temp variable) | E2: Write in Java, then check on HackerRank (Java domain) | F2: Not Started
A3: 2 | B3: 1 | C3: Java basics, I/O and conditions | D3: Largest of three numbers | E3: Write in Java, then check on HackerRank (Java domain) | F3: Not Started
A4: 3 | B4: 1 | C4: Java basics, I/O and conditions | D4: Check leap year | E4: Write in Java, then check on HackerRank (Java domain) | F4: Not Started
A5: 4 | B5: 1 | C5: Java basics, I/O and conditions | D5: Check even or odd | E5: Write in Java, then check on HackerRank (Java domain) | F5: Not Started
A6: 5 | B6: 1 | C6: Java basics, I/O and conditions | D6: Simple calculator using switch | E6: Write in Java, then check on HackerRank (Java domain) | F6: Not Started
A7: 6 | B7: 1 | C7: Java basics, I/O and conditions | D7: Grade calculator using if-else ladder | E7: Write in Java, then check on HackerRank (Java domain) | F7: Not Started
A8: 7 | B8: 1 | C8: Java basics, I/O and conditions | D8: Check vowel or consonant | E8: Write in Java, then check on HackerRank (Java domain) | F8: Not Started
A9: 8 | B9: 1 | C9: Java basics, I/O and conditions | D9: Convert temperature (Celsius to Fahrenheit) | E9: Write in Java, then check on HackerRank (Java domain) | F9: Not Started
A10: 9 | B10: 2 | C10: Loops and digit logic | D10: Sum of first N natural numbers | E10: GFG Basic / CodeChef FLOW series | F10: Not Started
A11: 10 | B11: 2 | C11: Loops and digit logic | D11: Factorial of a number | E11: GFG Basic / CodeChef FLOW series | F11: Not Started
A12: 11 | B12: 2 | C12: Loops and digit logic | D12: Multiplication table of N | E12: GFG Basic / CodeChef FLOW series | F12: Not Started
A13: 12 | B13: 2 | C13: Loops and digit logic | D13: Count digits in a number | E13: GFG Basic / CodeChef FLOW series | F13: Not Started
... A90: 89 | B90: 10 | C90: Problem-solving method and mock round | D90: Mock round: solve 5 mixed problems from Days 1-9 in 45 minutes while explaining aloud | E90: Mixed: self-timed | F90: Not Started

Sheet Logic Plan & Interview
A1: Day | B1: Focus | C1: Skill you build | D1: Why interviewers care | E1: Time
A2: 1 | B2: Java basics, I/O and conditions | C2: Data types, operators, integer division, if/else, switch | D2: Warm-up questions in the first screening round. Shows you know int overflow and integer division traps. | E2: 2 hrs
A3: 2 | B3: Loops and digit logic | C3: Using % 10 and / 10 to pull digits apart | D3: Digit logic is the base for 20+ problems (palindrome, Armstrong, reverse). Asked in almost every fresher test. | E3: 2 hrs
A4: 3 | B4: Number theory logic | C4: Prime up to sqrt(n), Euclid's GCD, base conversion | D4: Shows you can optimize brute force and talk about time complexity. | E4: 2 hrs
A5: 4 | B5: Star patterns | C5: Nested loops, mapping rows and columns to spaces and stars | D5: Common in written tests of service companies. Tests whether you can break a picture into row and column rules. | E5: 2 hrs
A6: 5 | B6: Number and alphabet patterns | C6: Row/column formulas, Pascal's triangle with previous row | D6: Tests careful thinking and dry running, not just syntax. | E6: 2 hrs
A7: 6 | B7: Array logic (1D) | C7: Single-pass scans, two variables (max, second max), in-place changes | D7: Arrays are the most-asked topic. Interviewers want a one-pass solution, not sort-then-pick. | E7: 2.5 hrs
A8: 7 | B8: 2D arrays and basic sorting | C8: Row/column indexing, swapping, loop invariants | D8: Matrix and sorting questions test index handling. Explaining bubble vs selection vs insertion is a common viva question. | E8: 2.5 hrs
A9: 8 | B9: String logic | C9: char arithmetic, frequency array, StringBuilder, split | D9: Strings are the second most-asked topic. You will be asked String vs StringBuilder vs StringBuffer. | E9: 2.5 hrs
A10: 9 | B10: Recursion and Java collections | C10: Base case and recursive case, HashMap, HashSet, Comparator | D10: Full-stack Java interviews mix coding with collections. Recursion is the bridge to trees and backtracking later. | E10: 2.5 hrs
A11: 10 | B11: Problem-solving method and mock round | C11: Brute force to optimized, complexity, dry run, speaking aloud | D11: This is what separates a prepared candidate from one who memorized answers. | E11: 3 hrs
A13: How to solve any problem in an interview (use these 8 steps every time)
A14: Step | B14: What to do | C14: What to say out loud | D14: Why it matters
A15: 1 | B15: Understand the problem | C15: 'Let me restate it: the input is..., the output should be...' | D15: Prevents solving the wrong problem. Ask about input size and whether duplicates or negatives are allowed.
A16: 2 | B16: Work through 1-2 examples by hand | C16: 'For input [2, 7, 11], the answer should be...' | D16: Reveals the pattern before you write any code.
A17: 3 | B17: Say the brute force first | C17: 'The simple way is two loops, which is O(n^2).' | D17: Shows you can always produce a working answer, then improve it.
A18: 4 | B18: Optimize and name the idea | C18: 'I can use a HashMap to cut this to O(n) time with O(n) extra space.' | D18: Interviewers listen for the trade-off between time and space.
A19: 5 | B19: List edge cases | C19: 'Empty array, one element, all same values, negative numbers, overflow.' | D19: Edge cases are where most fresher solutions fail.
A20: 6 | B20: Write clean Java code | C20: Use meaningful variable names and small steps. | D20: Readable code signals you can work in a team codebase.
A21: 7 | B21: Dry run with your example | C21: 'With i = 0, map is empty, so I store 2...' | D21: Catches your own bugs before the interviewer does.
A22: 8 | B22: State time and space complexity | C22: 'Time O(n), space O(n).' | D22: Always asked at the end. Say it before they ask.
A24: Edge-case checklist
B25: Empty input or null (arrays, strings, lists)
B26: Single element
B27: All elements equal / duplicates present
B28: Negative numbers and zero
B29: int overflow: use long when sums or products can be large
B30: Already sorted / reverse sorted input
B31: Very large input: check your time complexity

Sheet LeetCode Tracker
A1: S.No | B1: Week | C1: Phase | D1: Topic | E1: LC No | F1: Problem Name | G1: Difficulty | H1: Status | I1: Date Solved | J1: Notes / Approach
A2: 1 | B2: 1 | C2: Phase 1: Foundations | D2: 1. Conditional Statements | E2: 412 | F2: Fizz Buzz | G2: Easy | H2: Not Started
A3: 2 | B3: 1 | C3: Phase 1: Foundations | D3: 1. Conditional Statements | E3: 1822 | F3: Sign of the Product of an Array | G3: Easy | H3: Not Started
A4: 3 | B4: 1 | C4: Phase 1: Foundations | D4: 1. Conditional Statements | E4: 1491 | F4: Average Salary Excluding the Minimum and Maximum Salary | G4: Easy | H4: Not Started
A5: 4 | B5: 1 | C5: Phase 1: Foundations | D5: 1. Conditional Statements | E5: 1523 | F5: Count Odd Numbers in an Interval Range | G5: Easy | H5: Solved | I5: 46322
A6: 5 | B6: 1 | C6: Phase 1: Foundations | D6: 1. Conditional Statements | E6: 976 | F6: Largest Perimeter Triangle | G6: Easy | H6: Not Started
A7: 6 | B7: 1 | C7: Phase 1: Foundations | D7: 1. Conditional Statements | E7: 836 | F7: Rectangle Overlap | G7: Easy | H7: Not Started
A8: 7 | B8: 1 | C8: Phase 1: Foundations | D8: 1. Conditional Statements | E8: 1185 | F8: Day of the Week | G8: Easy | H8: Not Started
A9: 8 | B9: 1 | C9: Phase 1: Foundations | D9: 1. Conditional Statements | E9: 1360 | F9: Number of Days Between Two Dates | G9: Easy | H9: Not Started
A10: 9 | B10: 1 | C10: Phase 1: Foundations | D10: 2. Loops and Basic Math | E10: 1672 | F10: Richest Customer Wealth | G10: Easy | H10: Not Started
A11: 10 | B11: 1 | C11: Phase 1: Foundations | D11: 2. Loops and Basic Math | E11: 1342 | F11: Number of Steps to Reduce a Number to Zero | G11: Easy | H11: Not Started
A12: 11 | B12: 1 | C12: Phase 1: Foundations | D12: 2. Loops and Basic Math | E12: 1281 | F12: Subtract the Product and Sum of Digits of an Integer | G12: Easy | H12: Not Started
A13: 12 | B13: 1 | C13: Phase 1: Foundations | D13: 2. Loops and Basic Math | E13: 258 | F13: Add Digits | G13: Easy | H13: Not Started
A14: 13 | B14: 1 | C14: Phase 1: Foundations | D14: 2. Loops and Basic Math | E14: 1688 | F14: Count of Matches in Tournament | G14: Easy | H14: Not Started
A15: 14 | B15: 1 | C15: Phase 1: Foundations | D15: 2. Loops and Basic Math | E15: 1518 | F15: Water Bottles | G15: Easy | H15: Not Started
A16: 15 | B16: 1 | C16: Phase 1: Foundations | D16: 2. Loops and Basic Math | E16: 509 | F16: Fibonacci Number | G16: Easy | H16: Not Started
A17: 16 | B17: 1 | C17: Phase 1: Foundations | D17: 2. Loops and Basic Math | E17: 9 | F17: Palindrome Number | G17: Easy | H17: Not Started
... A209: 208 | B209: 16 | C209: Phase 4: Advanced | D209: 21. Very Advanced | E209: 887 | F209: Super Egg Drop | G209: Hard | H209: Not Started

Sheet Extra Practice
A1: S.No | B1: Week | C1: Topic | D1: Platform | E1: Problem Name | F1: Status | G1: Date Solved | H1: Notes
A2: 1 | B2: 1 | C2: Conditions, Loops, Math | D2: HackerRank | E2: Java If-Else | F2: Not Started
A3: 2 | B3: 1 | C3: Conditions, Loops, Math | D3: HackerRank | E3: Java Loops I | F3: Not Started
A4: 3 | B4: 1 | C4: Conditions, Loops, Math | D4: HackerRank | E4: Java Loops II | F4: Not Started
A5: 4 | B5: 1 | C5: Conditions, Loops, Math | D5: GFG | E5: Check Prime | F5: Not Started
A6: 5 | B6: 1 | C6: Conditions, Loops, Math | D6: GFG | E6: GCD and LCM | F6: Not Started
A7: 6 | B7: 1 | C7: Conditions, Loops, Math | D7: GFG | E7: Armstrong Number | F7: Not Started
A8: 7 | B8: 1 | C8: Conditions, Loops, Math | D8: GFG | E8: Factorial Trailing Zeroes | F8: Not Started
A9: 8 | B9: 1 | C9: Conditions, Loops, Math | D9: GFG | E9: Pattern Printing | F9: Not Started
A10: 9 | B10: 1 | C10: Conditions, Loops, Math | D10: CodeChef | E10: FLOW001 - Add Two Numbers | F10: Not Started
A11: 10 | B11: 1 | C11: Conditions, Loops, Math | D11: CodeChef | E11: FLOW006 - Sum of Digits | F11: Not Started
A12: 11 | B12: 1 | C12: Conditions, Loops, Math | D12: CodeChef | E12: FLOW007 - Reverse the Number | F12: Not Started
A13: 12 | B13: 2 | C13: Arrays | D13: GFG | E13: Second Largest Element | F13: Not Started
... A130: 129 | B130: 16 | C130: Advanced and Revision | D130: LeetCode | E130: Weekly Contest - Mock Test 3 | F130: Not Started
